!lab1/DMUX1to16.vhd
library IEEE;
use IEEE.STD_LOGIC_1164.ALL;

entity DMUX1to16 is
    Port (
        D : in STD_LOGIC;
        S : in STD_LOGIC_VECTOR(3 downto 0);
        Y : out STD_LOGIC_VECTOR(15 downto 0)
    );
end DMUX1to16;

architecture GateLevel of DMUX1to16 is
begin

    Y(0)  <= D and (not S(3)) and (not S(2)) and (not S(1)) and (not S(0));
    Y(1)  <= D and (not S(3)) and (not S(2)) and (not S(1)) and      S(0);
    Y(2)  <= D and (not S(3)) and (not S(2)) and      S(1)  and (not S(0));
    Y(3)  <= D and (not S(3)) and (not S(2)) and      S(1)  and      S(0);

    Y(4)  <= D and (not S(3)) and      S(2)  and (not S(1)) and (not S(0));
    Y(5)  <= D and (not S(3)) and      S(2)  and (not S(1)) and      S(0);
    Y(6)  <= D and (not S(3)) and      S(2)  and      S(1)  and (not S(0));
    Y(7)  <= D and (not S(3)) and      S(2)  and      S(1)  and      S(0);

    Y(8)  <= D and      S(3)  and (not S(2)) and (not S(1)) and (not S(0));
    Y(9)  <= D and      S(3)  and (not S(2)) and (not S(1)) and      S(0);
    Y(10) <= D and      S(3)  and (not S(2)) and      S(1)  and (not S(0));
    Y(11) <= D and      S(3)  and (not S(2)) and      S(1)  and      S(0);

    Y(12) <= D and      S(3)  and      S(2)  and (not S(1)) and (not S(0));
    Y(13) <= D and      S(3)  and      S(2)  and (not S(1)) and      S(0);
    Y(14) <= D and      S(3)  and      S(2)  and      S(1)  and (not S(0));
    Y(15) <= D and      S(3)  and      S(2)  and      S(1)  and      S(0);

end GateLevel;

!lab1/tb_DMUX1to16.vhd
library IEEE;
use IEEE.STD_LOGIC_1164.ALL;

entity tb_DMUX1to16 is
end tb_DMUX1to16;

architecture sim of tb_DMUX1to16 is

    signal D : STD_LOGIC;
    signal S : STD_LOGIC_VECTOR(3 downto 0);
    signal Y0  : STD_LOGIC;
    signal Y1  : STD_LOGIC;
    signal Y2  : STD_LOGIC;
    signal Y3  : STD_LOGIC;
    signal Y4  : STD_LOGIC;
    signal Y5  : STD_LOGIC;
    signal Y6  : STD_LOGIC;
    signal Y7  : STD_LOGIC;
    signal Y8  : STD_LOGIC;
    signal Y9  : STD_LOGIC;
    signal Y10 : STD_LOGIC;
    signal Y11 : STD_LOGIC;
    signal Y12 : STD_LOGIC;
    signal Y13 : STD_LOGIC;
    signal Y14 : STD_LOGIC;
    signal Y15 : STD_LOGIC;

begin

    uut : entity work.DMUX1to16
    port map (
        D => D,
        S => S,
        Y => Y
    );

    process
    begin

        D <= '1';

        S <= "0000";
        wait for 10 ns;

        S <= "0001";
        wait for 10 ns;

        S <= "0010";
        wait for 10 ns;

        S <= "0011";
        wait for 10 ns;

        S <= "0100";
        wait for 10 ns;

        S <= "0101";
        wait for 10 ns;

        S <= "0110";
        wait for 10 ns;

        S <= "0111";
        wait for 10 ns;

        S <= "1000";
        wait for 10 ns;

        S <= "1001";
        wait for 10 ns;

        S <= "1010";
        wait for 10 ns;

        S <= "1011";
        wait for 10 ns;

        S <= "1100";
        wait for 10 ns;

        S <= "1101";
        wait for 10 ns;

        S <= "1110";
        wait for 10 ns;

        S <= "1111";
        wait for 10 ns;

        D <= '0';

        wait;

    end process;

end sim;

!lab1/dmux.vcd
$date
  Thu Jul 16 23:42:12 2026
$end
$version
  GHDL v0
$end
$timescale
  1 fs
$end
$scope module standard $end
$upscope $end
$scope module std_logic_1164 $end
$upscope $end
$scope module tb_dmux1to16 $end
$var reg 1 ! d $end
$var reg 4 " s[3:0] $end
$var reg 16 # y[15:0] $end
$scope module uut $end
$var reg 1 $ d $end
$var reg 4 % s[3:0] $end
$var reg 16 & y[15:0] $end
$upscope $end
$upscope $end
$enddefinitions $end
#0
1!
b0000 "
b0000000000000001 #
1$
b0000 %
b0000000000000001 &
#10000000
b0001 "
b0000000000000010 #
b0001 %
b0000000000000010 &
#20000000
b0010 "
b0000000000000100 #
b0010 %
b0000000000000100 &
#30000000
b0011 "
b0000000000001000 #
b0011 %
b0000000000001000 &
#40000000
b0100 "
b0000000000010000 #
b0100 %
b0000000000010000 &
#50000000
b0101 "
b0000000000100000 #
b0101 %
b0000000000100000 &
#60000000
b0110 "
b0000000001000000 #
b0110 %
b0000000001000000 &
#70000000
b0111 "
b0000000010000000 #
b0111 %
b0000000010000000 &
#80000000
b1000 "
b0000000100000000 #
b1000 %
b0000000100000000 &
#90000000
b1001 "
b0000001000000000 #
b1001 %
b0000001000000000 &
#100000000
b1010 "
b0000010000000000 #
b1010 %
b0000010000000000 &
#110000000
b1011 "
b0000100000000000 #
b1011 %
b0000100000000000 &
#120000000
b1100 "
b0001000000000000 #
b1100 %
b0001000000000000 &
#130000000
b1101 "
b0010000000000000 #
b1101 %
b0010000000000000 &
#140000000
b1110 "
b0100000000000000 #
b1110 %
b0100000000000000 &
#150000000
b1111 "
b1000000000000000 #
b1111 %
b1000000000000000 &
#160000000
0!
b0000000000000000 #
0$
b0000000000000000 &
