!lab1/MUX16to1.vhd
library IEEE;
use IEEE.STD_LOGIC_1164.ALL;

entity MUX16to1 is
    Port (
        D : in  STD_LOGIC_VECTOR(15 downto 0);
        S : in  STD_LOGIC_VECTOR(3 downto 0);
        Y : out STD_LOGIC
    );
end MUX16to1;

architecture Behavioral of MUX16to1 is
begin

    with S select
        Y <= D(0)  when "0000",
             D(1)  when "0001",
             D(2)  when "0010",
             D(3)  when "0011",
             D(4)  when "0100",
             D(5)  when "0101",
             D(6)  when "0110",
             D(7)  when "0111",
             D(8)  when "1000",
             D(9)  when "1001",
             D(10) when "1010",
             D(11) when "1011",
             D(12) when "1100",
             D(13) when "1101",
             D(14) when "1110",
             D(15) when "1111",
             '0'   when others;

end Behavioral;

!lab1/tb_MUX16to1.vhd
library IEEE;
use IEEE.STD_LOGIC_1164.ALL;

entity tb_MUX16to1 is
end tb_MUX16to1;

architecture sim of tb_MUX16to1 is

    signal D0  : STD_LOGIC := '0';
    signal D1  : STD_LOGIC := '0';
    signal D2  : STD_LOGIC := '0';
    signal D3  : STD_LOGIC := '0';
    signal D4  : STD_LOGIC := '0';
    signal D5  : STD_LOGIC := '0';
    signal D6  : STD_LOGIC := '0';
    signal D7  : STD_LOGIC := '0';
    signal D8  : STD_LOGIC := '0';
    signal D9  : STD_LOGIC := '0';
    signal D10 : STD_LOGIC := '0';
    signal D11 : STD_LOGIC := '0';
    signal D12 : STD_LOGIC := '0';
    signal D13 : STD_LOGIC := '0';
    signal D14 : STD_LOGIC := '0';
    signal D15 : STD_LOGIC := '0';

    signal D : STD_LOGIC_VECTOR(15 downto 0);

    signal S : STD_LOGIC_VECTOR(3 downto 0);
    signal Y : STD_LOGIC;

begin

    -- รวมสัญญาณ D0-D15 เป็น Bus
    D <= D15 & D14 & D13 & D12 &
         D11 & D10 & D9  & D8  &
         D7  & D6  & D5  & D4  &
         D3  & D2  & D1  & D0;

    uut : entity work.MUX16to1
    port map (
        D => D,
        S => S,
        Y => Y
    );

    process
    begin

        D0 <= '1'; S <= "0000";
        wait for 10 ns;
        D0 <= '0';

        D1 <= '1'; S <= "0001";
        wait for 10 ns;
        D1 <= '0';

        D2 <= '1'; S <= "0010";
        wait for 10 ns;
        D2 <= '0';

        D3 <= '1'; S <= "0011";
        wait for 10 ns;
        D3 <= '0';

        D4 <= '1'; S <= "0100";
        wait for 10 ns;
        D4 <= '0';

        D5 <= '1'; S <= "0101";
        wait for 10 ns;
        D5 <= '0';

        D6 <= '1'; S <= "0110";
        wait for 10 ns;
        D6 <= '0';

        D7 <= '1'; S <= "0111";
        wait for 10 ns;
        D7 <= '0';

        D8 <= '1'; S <= "1000";
        wait for 10 ns;
        D8 <= '0';

        D9 <= '1'; S <= "1001";
        wait for 10 ns;
        D9 <= '0';

        D10 <= '1'; S <= "1010";
        wait for 10 ns;
        D10 <= '0';

        D11 <= '1'; S <= "1011";
        wait for 10 ns;
        D11 <= '0';

        D12 <= '1'; S <= "1100";
        wait for 10 ns;
        D12 <= '0';

        D13 <= '1'; S <= "1101";
        wait for 10 ns;
        D13 <= '0';

        D14 <= '1'; S <= "1110";
        wait for 10 ns;
        D14 <= '0';

        D15 <= '1'; S <= "1111";
        wait for 10 ns;
        D15 <= '0';

        wait;

    end process;

end sim;

!lab1/mux.vcd
$date
  Thu Jul 16 21:56:03 2026
$end
$version
  GHDL v0
$end
$timescale
  1 fs
$end
$scope module standard $end
$upscope $end
$scope module std_logic_1164 $end
$upscope $end
$scope module tb_mux16to1 $end
$var reg 1 ! d0 $end
$var reg 1 " d1 $end
$var reg 1 # d2 $end
$var reg 1 $ d3 $end
$var reg 1 % d4 $end
$var reg 1 & d5 $end
$var reg 1 ' d6 $end
$var reg 1 ( d7 $end
$var reg 1 ) d8 $end
$var reg 1 * d9 $end
$var reg 1 + d10 $end
$var reg 1 , d11 $end
$var reg 1 - d12 $end
$var reg 1 . d13 $end
$var reg 1 / d14 $end
$var reg 1 0 d15 $end
$var reg 16 1 d[15:0] $end
$var reg 4 2 s[3:0] $end
$var reg 1 3 y $end
$scope module uut $end
$var reg 16 4 d[15:0] $end
$var reg 4 5 s[3:0] $end
$var reg 1 6 y $end
$upscope $end
$upscope $end
$enddefinitions $end
#0
1!
0"
0#
0$
0%
0&
0'
0(
0)
0*
0+
0,
0-
0.
0/
00
b0000000000000001 1
b0000 2
13
b0000000000000001 4
b0000 5
16
#10000000
0!
1"
b0000000000000010 1
b0001 2
13
b0000000000000010 4
b0001 5
16
#20000000
0"
1#
b0000000000000100 1
b0010 2
13
b0000000000000100 4
b0010 5
16
#30000000
0#
1$
b0000000000001000 1
b0011 2
13
b0000000000001000 4
b0011 5
16
#40000000
0$
1%
b0000000000010000 1
b0100 2
13
b0000000000010000 4
b0100 5
16
#50000000
0%
1&
b0000000000100000 1
b0101 2
13
b0000000000100000 4
b0101 5
16
#60000000
0&
1'
b0000000001000000 1
b0110 2
13
b0000000001000000 4
b0110 5
16
#70000000
0'
1(
b0000000010000000 1
b0111 2
13
b0000000010000000 4
b0111 5
16
#80000000
0(
1)
b0000000100000000 1
b1000 2
13
b0000000100000000 4
b1000 5
16
#90000000
0)
1*
b0000001000000000 1
b1001 2
13
b0000001000000000 4
b1001 5
16
#100000000
0*
1+
b0000010000000000 1
b1010 2
13
b0000010000000000 4
b1010 5
16
#110000000
0+
1,
b0000100000000000 1
b1011 2
13
b0000100000000000 4
b1011 5
16
#120000000
0,
1-
b0001000000000000 1
b1100 2
13
b0001000000000000 4
b1100 5
16
#130000000
0-
1.
b0010000000000000 1
b1101 2
13
b0010000000000000 4
b1101 5
16
#140000000
0.
1/
b0100000000000000 1
b1110 2
13
b0100000000000000 4
b1110 5
16
#150000000
0/
10
b1000000000000000 1
b1111 2
13
b1000000000000000 4
b1111 5
16
#160000000
00
b0000000000000000 1
03
b0000000000000000 4
06
